chat_cli_anything/__init__.py
chat_cli_anything/ask.py
chat_cli_anything/config.py
chat_cli_anything/db.py
chat_cli_anything/embedding.py
chat_cli_anything/loader.py
chat_cli_anything/request.py
chat_cli_anything/rerank.py
chat_cli_anything/service.py
chat_cli_anything/util.py
chat_cli_anything-0.1.8.dist-info/LICENSE
chat_cli_anything-0.1.8.dist-info/METADATA
chat_cli_anything-0.1.8.dist-info/WHEEL
chat_cli_anything-0.1.8.dist-info/entry_points.txt
chat_cli_anything-0.1.8.dist-info/RECORD
