Metadata-Version: 2.1
Name: chat-cli-anything
Version: 0.1.8
Summary: Chat with anything on cli.
License: Apache
Keywords: chatgpt,cli,chat
Author: liuping
Author-email: liuping@shukun.net
Requires-Python: >=3.9,<4.0
Classifier: License :: Other/Proprietary License
Classifier: Programming Language :: Python :: 3
Classifier: Programming Language :: Python :: 3.9
Classifier: Programming Language :: Python :: 3.10
Classifier: Programming Language :: Python :: 3.11
Classifier: Programming Language :: Python :: 3.12
Provides-Extra: all
Requires-Dist: click (>=8.1.7,<9.0.0)
Requires-Dist: faiss-cpu (>=1.8.0,<2.0.0)
Requires-Dist: fastapi (>=0.110.0,<0.111.0)
Requires-Dist: flagembedding (>=1.2.8,<2.0.0) ; extra == "all"
Requires-Dist: langchain (>=0.1.13,<0.2.0) ; extra == "all"
Requires-Dist: langchain-community (>=0.0.29,<0.0.30) ; extra == "all"
Requires-Dist: langchain-core (>=0.1.36,<0.2.0)
Requires-Dist: langchain-openai (>=0.1.1,<0.2.0) ; extra == "all"
Requires-Dist: langchain-text-splitters (>=0.0.1,<0.0.2) ; extra == "all"
Requires-Dist: openai (>=1.13.3,<2.0.0)
Requires-Dist: psutil (>=5.9.8,<6.0.0)
Requires-Dist: pypdf (>=4.1.0,<5.0.0)
Requires-Dist: requests (>=2.31.0,<3.0.0)
Requires-Dist: rich (>=13.7.1,<14.0.0)
Requires-Dist: tabulate (>=0.9.0,<0.10.0)
Requires-Dist: tiktoken (>=0.6.0,<0.7.0)
Requires-Dist: torch (>=2.1.0) ; extra == "all"
Requires-Dist: tqdm (>=4.66.2,<5.0.0)
Requires-Dist: uvicorn (>=0.29.0,<0.30.0)
Requires-Dist: xonsh (>=0.15.1,<0.16.0)
